<?xml version="1.0" ?><list><model.User><name>agsf</name><password>8</password><email>8</email><Id>ag@1</Id><job>Student</job><gender>true</gender><date>2024-07-04</date><age>0</age><enrolledCourses></enrolledCourses></model.User><model.User><name> 333</name><password>8</password><email>8</email><Id> 3@2</Id><job>Student</job><gender>true</gender><date>2024-07-04</date><age>0</age><enrolledCourses></enrolledCourses></model.User><model.User><name>amgad2</name><password>123</password><email>amgad2</email><Id>am@3</Id><job>Software Developer/Engineer</job><gender>true</gender><date>2024-07-16</date><age>0</age><profilePath>file:/C:/Users/amgad/OneDrive/Desktop/IMG_20240517_033358_085.jpg</profilePath><enrolledCourses></enrolledCourses></model.User><model.User><name>aa</name><password>aa</password><email>aa</email><Id>aa@4</Id><job>Software Developer/Engineer</job><gender>true</gender><date>2024-07-03</date><age>0</age><enrolledCourses></enrolledCourses></model.User><model.User><name>agsf</name><password>8</password><email>8</email><Id>ag@5</Id><job>Student</job><gender>true</gender><date>2024-07-05</date><age>0</age><enrolledCourses></enrolledCourses></model.User><model.User><name> 333</name><password>8</password><email>8</email><Id> 3@6</Id><job>Student</job><gender>true</gender><date>2024-07-05</date><age>0</age><enrolledCourses></enrolledCourses></model.User><model.User><name>asda</name><password>sdad</password><email>asda</email><Id>as@7</Id><job>Data Scientist</job><gender>true</gender><date>2024-07-03</date><age>0</age><enrolledCourses></enrolledCourses></model.User><model.User><name>dsdf</name><password>fsd</password><email>dsf</email><Id>ds@8</Id><job>Data Scientist</job><gender>true</gender><date>2024-07-09</date><age>0</age><profilePath>file:/C:/Users/amgad/OneDrive/Desktop/IMG_20240517_033358_085.jpg</profilePath><enrolledCourses></enrolledCourses></model.User><model.User><name>dfg</name><password>fgfd</password><email>fgdfgg</email><Id>df@9</Id><job>Software Developer/Engineer</job><gender>true</gender><date>2024-07-03</date><age>0</age><profilePath>file:/C:/Users/amgad/OneDrive/Desktop/IMG_20240517_033358_085.jpg</profilePath><enrolledCourses></enrolledCourses></model.User><model.User><name>momo</name><password>126633</password><email>momo@gmail.com</email><Id>mo@10</Id><job>Student</job><gender>true</gender><date>2003-07-09</date><age>21</age><enrolledCourses></enrolledCourses></model.User></list>